aptosconnector/__init__.py
aptosconnector/setup.py
aptosconnector/upload.py
aptosconnector/validate.py
aptosconnector/utils/__init__.py
aptosconnector/utils/aws.py
aptosconnector/utils/cli.py
aptosconnector/utils/file_sha256.py
aptosconnector/utils/hash_dataset.py
AptosConnector-0.0.2.dist-info/LICENSE.txt
AptosConnector-0.0.2.dist-info/METADATA
AptosConnector-0.0.2.dist-info/WHEEL
AptosConnector-0.0.2.dist-info/entry_points.txt
AptosConnector-0.0.2.dist-info/top_level.txt
AptosConnector-0.0.2.dist-info/RECORD
