Metadata-Version: 2.1
Name: AptosConnector
Version: 0.0.2
Summary: A dataset validation and upload utility for Aptos
Author-email: Jeremi Wojcicki <jeremi@etacompute.com>, Vedin Klovo <vedin.klovo@etacompute.com>
License: Copyright (c) 2023 Eta Compute Inc.
Project-URL: Homepage, https://github.com/Eta-Compute/AptosConnector
Project-URL: Bug Reports, https://github.com/Eta-Compute/AptosConnector/issues
Project-URL: Source, https://github.com/Eta-Compute/AptosConnector
Keywords: aptos,dataset,connector,upload
Classifier: Development Status :: 3 - Alpha
Classifier: Intended Audience :: Developers
Classifier: Topic :: Scientific/Engineering :: Artificial Intelligence
Classifier: License :: OSI Approved :: MIT License
Classifier: Programming Language :: Python :: 3
Classifier: Programming Language :: Python :: 3.8
Classifier: Programming Language :: Python :: 3.9
Classifier: Programming Language :: Python :: 3.10
Classifier: Programming Language :: Python :: 3.11
Classifier: Programming Language :: Python :: 3 :: Only
Requires-Python: >=3.8
License-File: LICENSE.txt
Requires-Dist: numpy
Requires-Dist: tqdm
Requires-Dist: getpass-asterisk
Requires-Dist: checksumdir
Requires-Dist: scandir
Requires-Dist: pycocotools
Provides-Extra: dev
Requires-Dist: check-manifest ; extra == 'dev'
Provides-Extra: test
Requires-Dist: coverage ; extra == 'test'
